raven_hydro/__init__.py
raven_hydro/_core.cpython-38-x86_64-linux-gnu.so
raven_hydro-0.2.0.data/scripts/raven
raven_hydro-0.2.0.data/scripts/raven_COPYING
raven_hydro-0.2.0.dist-info/METADATA
raven_hydro-0.2.0.dist-info/WHEEL
raven_hydro-0.2.0.dist-info/entry_points.txt
raven_hydro-0.2.0.dist-info/licenses/LICENSE
raven_hydro-0.2.0.dist-info/RECORD
