Metadata-Version: 2.1
Name: raven-hydro
Version: 0.2.0
Summary: A Python wrapper to set-up and build the hydrologic modelling framework Raven.
Keywords: raven hydrologic model cmake
Author-Email: Trevor James Smith <smith.trevorj@ouranos.ca>
License:                                  Apache License
Classifier: Development Status :: 4 - Beta
Classifier: Intended Audience :: Developers
Classifier: Intended Audience :: Education
Classifier: Intended Audience :: Science/Research
Classifier: License :: OSI Approved :: Apache Software License
Classifier: Natural Language :: English
Classifier: Programming Language :: Python :: 3
Classifier: Programming Language :: Python :: 3.8
Classifier: Programming Language :: Python :: 3.9
Classifier: Programming Language :: Python :: 3.10
Classifier: Programming Language :: Python :: 3.11
Classifier: Programming Language :: Python
Classifier: Topic :: Scientific/Engineering :: Hydrology
Project-URL: About ouranos, https://www.ouranos.ca/en
Project-URL: About raven, http://raven.uwaterloo.ca/About.html
Project-URL: Homepage, https://github.com/Ouranosinc/raven-hydro
Project-URL: Issue tracker, https://github.com/Ouranosinc/raven-hydro/issues
Requires-Python: >=3.8
License-File: LICENSE
